r2/__init__.py
r2/r_anal.py
r2/r_asm.py
r2/r_bin.py
r2/r_bp.py
r2/r_config.py
r2/r_cons.py
r2/r_core.py
r2/r_crypto.py
r2/r_debug.py
r2/r_egg.py
r2/r_flag.py
r2/r_fs.py
r2/r_hash.py
r2/r_io.py
r2/r_lang.py
r2/r_libs.py
r2/r_magic.py
r2/r_main.py
r2/r_parse.py
r2/r_reg.py
r2/r_search.py
r2/r_socket.py
r2/r_syscall.py
r2/r_util.py
r2/libr/libr_anal.so
r2/libr/libr_anal.so.5.2.0
r2/libr/libr_asm.so
r2/libr/libr_asm.so.5.2.0
r2/libr/libr_bin.so
r2/libr/libr_bin.so.5.2.0
r2/libr/libr_bp.so
r2/libr/libr_bp.so.5.2.0
r2/libr/libr_config.so
r2/libr/libr_config.so.5.2.0
r2/libr/libr_cons.so
r2/libr/libr_cons.so.5.2.0
r2/libr/libr_core.so
r2/libr/libr_core.so.5.2.0
r2/libr/libr_crypto.so
r2/libr/libr_crypto.so.5.2.0
r2/libr/libr_debug.so
r2/libr/libr_debug.so.5.2.0
r2/libr/libr_egg.so
r2/libr/libr_egg.so.5.2.0
r2/libr/libr_flag.so
r2/libr/libr_flag.so.5.2.0
r2/libr/libr_fs.so
r2/libr/libr_fs.so.5.2.0
r2/libr/libr_hash.so
r2/libr/libr_hash.so.5.2.0
r2/libr/libr_io.so
r2/libr/libr_io.so.5.2.0
r2/libr/libr_lang.so
r2/libr/libr_lang.so.5.2.0
r2/libr/libr_magic.so
r2/libr/libr_magic.so.5.2.0
r2/libr/libr_main.so
r2/libr/libr_main.so.5.2.0
r2/libr/libr_parse.so
r2/libr/libr_parse.so.5.2.0
r2/libr/libr_reg.so
r2/libr/libr_reg.so.5.2.0
r2/libr/libr_search.so
r2/libr/libr_search.so.5.2.0
r2/libr/libr_socket.so
r2/libr/libr_socket.so.5.2.0
r2/libr/libr_syscall.so
r2/libr/libr_syscall.so.5.2.0
r2/libr/libr_util.so
r2/libr/libr_util.so.5.2.0
pyr2-2.0.0.dist-info/LICENSE
pyr2-2.0.0.dist-info/METADATA
pyr2-2.0.0.dist-info/WHEEL
pyr2-2.0.0.dist-info/top_level.txt
pyr2-2.0.0.dist-info/RECORD
