Metadata-Version: 2.1
Name: pyr2
Version: 2.0.0
Summary: Yet anohter radare2 python bindings.
Home-page: https://github.com/wtdcode/pyr2
Author: mio
Author-email: mio@lazym.io
License: UNKNOWN
Platform: UNKNOWN
Classifier: Programming Language :: Python :: 3
Requires-Python: >=3.6
